aiopagination/__init__.py
aiopagination/aiokeyboards.py
aiopagination/aiopagination.py
test/__init__.py
aiopagination-1.0.2.dist-info/LICENSE.txt
aiopagination-1.0.2.dist-info/METADATA
aiopagination-1.0.2.dist-info/WHEEL
aiopagination-1.0.2.dist-info/top_level.txt
aiopagination-1.0.2.dist-info/RECORD
