Metadata-Version: 2.1
Name: aiopagination
Version: 1.0.2
Summary: A library designed to build pagination using the aiogram library
Home-page: https://github.com/Raxmatillo/aiopagination
Author: Rakhmatullo Shermatov
Author-email: Rakhmatullo Shermatov <milodcomposer@gmail.com>
Project-URL: Homepage, https://github.com/Raxmatillo/aiopagination
Project-URL: Bug Tracker, https://github.com/Raxmatillo/aiopagination/issues
Classifier: Programming Language :: Python :: 3
Classifier: License :: OSI Approved :: MIT License
Classifier: Operating System :: OS Independent
Requires-Python: >=3.6
License-File: LICENSE.txt
